README.rst
setup.py
Hippodamia.egg-info/PKG-INFO
Hippodamia.egg-info/SOURCES.txt
Hippodamia.egg-info/dependency_links.txt
Hippodamia.egg-info/entry_points.txt
Hippodamia.egg-info/requires.txt
Hippodamia.egg-info/top_level.txt
hippodamia/__init__.py
hippodamia/commands.py
hippodamia/enums.py
hippodamia/getch.py
hippodamia/heartbeat.py
hippodamia/monitoringservice.py
hippodamia/mymongoclient.py
hippodamia/onboarding.py
hippodamia/ui.py
hippodamia/agentshadow/__init__.py
hippodamia/agentshadow/agentshadow.py
hippodamia/agentshadow/agentshadowfactory.py
hippodamia/agentshadow/logarchive.py
hippodamia/agentshadow/messagearchive.py
hippodamia/agentshadow/properties.py
hippodamia/agentshadow/states/__init__.py
hippodamia/agentshadow/states/active.py
hippodamia/agentshadow/states/amonitoringstate.py
hippodamia/agentshadow/states/archivecandidate.py
hippodamia/agentshadow/states/archived.py
hippodamia/agentshadow/states/event_ids.py
hippodamia/agentshadow/states/inactive.py
hippodamia/agentshadow/states/lost.py
hippodamia/agentshadow/states/machinelogger.py
hippodamia/agentshadow/states/onboarded.py
hippodamia/agentshadow/states/onboarding.py
hippodamia/agentshadow/states/predefined.py
hippodamia/agentshadow/states/state_ids.py
hippodamia/agentshadow/states/state_machine.py
hippodamia/agentshadow/states/stopped.py
hippodamia/email/__init__.py
hippodamia/email/ainfo.py
hippodamia/email/anotifier.py
hippodamia/email/digest.py
hippodamia/email/emailnotification.py
hippodamia/email/minimal.py
hippodamia/email/sendemail.py
hippodamia/email/spontaneous.py
hippodamia/flask/__init__.py
hippodamia/flask/server.py
hippodamia/flask/serverthread.py
hippodamia/hierarchivalview/__init__.py
hippodamia/hierarchivalview/hierarchicalview.py
hippodamia/hierarchivalview/treebranch.py
hippodamia/hierarchivalview/treeentry.py
hippodamia/hierarchivalview/treeleaf.py
hippodamia/hierarchivalview/treeroot.py
hippodamia/schema/__init__.py
hippodamia/schema/agent_timings.py
hippodamia/schema/email.py
hippodamia/schema/expected_services.py
hippodamia/schema/mongodb.py
hippodamia/schema/monitoringservice.py
hippodamia/schema/service_timings.py
hippodamia/schema/topics.py
hippodamia/schema/webserver.py
