Metadata-Version: 1.2
Name: Hippodamia
Version: 0.4.2
Summary: Hippodamia observe the state of all registered microservices (aka watch dog).
Home-page: https://gitlab.com/pelops/hippodamia/
Author: Tobias Gawron-Deutsch
Author-email: tobias@strix.at
License: MIT license
Keywords: mqtt microservice monitoring service
Platform: UNKNOWN
Classifier: Development Status :: 4 - Beta
Classifier: Environment :: Console
Classifier: Environment :: No Input/Output (Daemon)
Classifier: Intended Audience :: Developers
Classifier: Programming Language :: Python :: 3
Classifier: Topic :: Utilities
Classifier: Topic :: Home Automation
Classifier: License :: OSI Approved :: MIT License
Requires-Python: >=3.5
